{
  "dct_title_s": "Lincoln Urban Area Floodways and Flood Plains",
  "dct_alternative_sm": [
    "Floodplains"
  ],
  "dct_description_sm": [
    "Lincoln Map Future Urban Parks. Source: Preliminary Flood Insurance Rate Map and Flood Boundary and Floodway Map issued by the Federal Emergency Management Agency"
  ],
  "dct_language_sm": [
    "eng"
  ],
  "dct_publisher_sm": [
    "LPS Natural Resource District"
  ],
  "schema_provider_s": "University of Nebraska-Lincoln",
  "gbl_resourceClass_sm": [
    "Maps"
  ],
  "dcat_keyword_sm": [
    "https://mediacommons.unl.edu/luna/servlet/iiif/m/UNL~126~126~14158~1515833/manifest"
  ],
  "dct_temporal_sm": [
    "1989"
  ],
  "dct_issued_s": "1990",
  "gbl_indexYear_im": [
    "1989"
  ],
  "gbl_dateRange_drsim": [
    "[1989 TO 1989]"
  ],
  "dct_spatial_sm": [
    "Nebraska--Lincoln",
    "Nebraska"
  ],
  "locn_geometry": "POLYGON((-96.914 41.048, -96.463 41.048, -96.463 40.523, -96.914 40.523, -96.914 41.048))",
  "dcat_bbox": "ENVELOPE(-96.914,-96.463,41.048,40.523)",
  "dcat_centroid": "40.7855,-96.6885",
  "pcdm_memberOf_sm": [
    "64bd8c4c-8e60-4956-b43d-bdc3f93db488"
  ],
  "dct_isPartOf_sm": [
    "13d-02"
  ],
  "dct_accessRights_s": "Public",
  "dct_format_s": "PDF",
  "dct_references_s": "{\"http://schema.org/url\":\"https://mediacommons.unl.edu/luna/servlet/detail/UNL~126~126~14158~1515833\",\"http://iiif.io/api/presentation#manifest\":\"https://mediacommons.unl.edu/luna/servlet/iiif/m/UNL~126~126~14158~1515833/manifest\"}",
  "id": "UNL_126_126_14158_1515833",
  "dct_identifier_sm": [
    "https://mediacommons.unl.edu/luna/servlet/s/u99nei"
  ],
  "gbl_mdVersion_s": "Aardvark"
}